medoo/__init__.py
medoo/base.py
medoo/builder.py
medoo/database/__init__.py
medoo/database/mssql.py
medoo/database/mysql.py
medoo/database/oracle.py
medoo/database/pgsql.py
medoo/database/sqlite.py
medoo/dialect.py
medoo/exception.py
medoo/record.py
medoo/util.py
medoo-0.1.2.dist-info/LICENSE
medoo-0.1.2.dist-info/WHEEL
medoo-0.1.2.dist-info/METADATA
medoo-0.1.2.dist-info/RECORD
