Metadata-Version: 2.1
Name: medoo
Version: 0.1.2
Summary: A lightweight database framework for python
Home-page: https://github.com/pwwang/pymedoo
License: MIT
Author: pwwang
Author-email: pwwang@pwwang.com
Requires-Python: >=3.7,<4.0
Classifier: License :: OSI Approved :: MIT License
Classifier: Programming Language :: Python :: 3
Classifier: Programming Language :: Python :: 3.7
Classifier: Programming Language :: Python :: 3.8
Classifier: Programming Language :: Python :: 3.9
Classifier: Programming Language :: Python :: 3.10
Classifier: Programming Language :: Python :: 3.11
Provides-Extra: all
Provides-Extra: mssql
Provides-Extra: mysql
Provides-Extra: oracle
Provides-Extra: postgresql
Requires-Dist: cx-Oracle (>=8,<9); extra == "all" or extra == "oracle"
Requires-Dist: mysql-connector-python (>=8,<9); extra == "all" or extra == "mysql"
Requires-Dist: psycopg2 (>=2,<3); extra == "all" or extra == "postgresql"
Requires-Dist: pymssql (>=2,<3); extra == "all" or extra == "mssql"
Project-URL: Repository, https://github.com/pwwang/pymedoo
